{"Author":"Secretaria de Finanças","Content-Length":"75305","Content-Type":"application/pdf","Creation-Date":"2020-02-13T17:41:05Z","Last-Modified":"2020-02-13T17:41:05Z","Last-Save-Date":"2020-02-13T17:41:05Z","X-Parsed-By":["org.apache.tika.parser.DefaultParser","org.apache.tika.parser.pdf.PDFParser"],"access_permission:assemble_document":"true","access_permission:can_modify":"true","access_permission:can_print":"true","access_permission:can_print_degraded":"true","access_permission:extract_content":"true","access_permission:extract_for_accessibility":"true","access_permission:fill_in_form":"true","access_permission:modify_annotations":"true","created":"2020-02-13T17:41:05Z","creator":"Secretaria de Finanças","date":"2020-02-13T17:41:05Z","dc:creator":"Secretaria de Finanças","dc:format":"application/pdf; version\u003d1.5","dc:language":"pt-BR","dc:title":"OF/002/2000/STD/SEFI","dcterms:created":"2020-02-13T17:41:05Z","dcterms:modified":"2020-02-13T17:41:05Z","language":"pt-BR","meta:author":"Secretaria de Finanças","meta:creation-date":"2020-02-13T17:41:05Z","meta:save-date":"2020-02-13T17:41:05Z","modified":"2020-02-13T17:41:05Z","pdf:PDFVersion":"1.5","pdf:charsPerPage":["3725","4566","274"],"pdf:docinfo:created":"2020-02-13T17:41:05Z","pdf:docinfo:creator":"Secretaria de Finanças","pdf:docinfo:creator_tool":"Microsoft® Word 2016","pdf:docinfo:modified":"2020-02-13T17:41:05Z","pdf:docinfo:producer":"Microsoft® Word 2016","pdf:docinfo:title":"OF/002/2000/STD/SEFI","pdf:encrypted":"false","pdf:hasMarkedContent":"true","pdf:hasXFA":"false","pdf:hasXMP":"false","pdf:unmappedUnicodeCharsPerPage":["0","0","0"],"producer":"Microsoft® Word 2016","resourceName":"5f35c4b449af9c3189469a192038b4479ef0dc02.pdf","title":"OF/002/2000/STD/SEFI","xmp:CreatorTool":"Microsoft® Word 2016","xmpTPg:NPages":"3"}