{"Application-Name":"Microsoft Office Word","Author":"Gabinete2","Character Count":"1193","Company":"","Content-Length":"105984","Content-Type":"application/msword","Creation-Date":"2020-07-22T18:59:00Z","Edit-Time":"1200000000","Keywords":"","Last-Author":"Usuario","Last-Modified":"2020-07-23T19:54:00Z","Last-Printed":"2020-07-23T19:54:00Z","Last-Save-Date":"2020-07-23T19:54:00Z","Page-Count":"1","Revision-Number":"3","Template":"Normal","Word-Count":"220","X-Parsed-By":["org.apache.tika.parser.DefaultParser","org.apache.tika.parser.microsoft.OfficeParser"],"cp:revision":"3","cp:subject":"","creator":"Gabinete2","date":"2020-07-23T19:54:00Z","dc:creator":"Gabinete2","dc:subject":"","dc:title":"DECRETO Nº","dcterms:created":"2020-07-22T18:59:00Z","dcterms:modified":"2020-07-23T19:54:00Z","extended-properties:Application":"Microsoft Office Word","extended-properties:Company":"","extended-properties:Template":"Normal","meta:author":"Gabinete2","meta:character-count":"1193","meta:creation-date":"2020-07-22T18:59:00Z","meta:keyword":"","meta:last-author":"Usuario","meta:page-count":"1","meta:print-date":"2020-07-23T19:54:00Z","meta:save-date":"2020-07-23T19:54:00Z","meta:word-count":"220","modified":"2020-07-23T19:54:00Z","resourceName":"07e7119e03727fea6050ae4831289eeafe7ed94c.doc","subject":"","title":"DECRETO Nº","xmpTPg:NPages":"1"}