{"Application-Name":"Microsoft Office Word","Application-Version":"15.0000","Author":"Wládia Travesani Marchezi","Character Count":"362","Character-Count-With-Spaces":"428","Content-Length":"12374","Content-Type":"application/vnd.openxmlformats-officedocument.wordprocessingml.document","Creation-Date":"2019-08-09T18:26:00Z","Last-Author":"Wládia Travesani Marchezi","Last-Modified":"2020-02-07T12:34:00Z","Last-Save-Date":"2020-02-07T12:34:00Z","Line-Count":"3","Page-Count":"1","Paragraph-Count":"1","Revision-Number":"11","Template":"Normal","Total-Time":"56","Word-Count":"67","X-Parsed-By":["org.apache.tika.parser.DefaultParser","org.apache.tika.parser.microsoft.ooxml.OOXMLParser"],"cp:revision":"11","creator":"Wládia Travesani Marchezi","date":"2020-02-07T12:34:00Z","dc:creator":"Wládia Travesani Marchezi","dc:publisher":"","dcterms:created":"2019-08-09T18:26:00Z","dcterms:modified":"2020-02-07T12:34:00Z","extended-properties:AppVersion":"15.0000","extended-properties:Application":"Microsoft Office Word","extended-properties:Company":"","extended-properties:DocSecurityString":"None","extended-properties:Template":"Normal","extended-properties:TotalTime":"56","meta:author":"Wládia Travesani Marchezi","meta:character-count":"362","meta:character-count-with-spaces":"428","meta:creation-date":"2019-08-09T18:26:00Z","meta:last-author":"Wládia Travesani Marchezi","meta:line-count":"3","meta:page-count":"1","meta:paragraph-count":"1","meta:save-date":"2020-02-07T12:34:00Z","meta:word-count":"67","modified":"2020-02-07T12:34:00Z","publisher":"","resourceName":"aed3edb2a86b0aece42d69034b5313a41abe1094.docx","xmpTPg:NPages":"1"}