{"Author":"marcia.souza","Content-Length":"56519","Content-Type":"application/rtf","Creation-Date":"2020-04-07T18:27:00Z","X-Parsed-By":["org.apache.tika.parser.DefaultParser","org.apache.tika.parser.rtf.RTFParser"],"creator":"marcia.souza","dc:creator":"marcia.souza","dcterms:created":"2020-04-07T18:27:00Z","meta:author":"marcia.souza","meta:character-count":"657","meta:creation-date":"2020-04-07T18:27:00Z","meta:page-count":"1","meta:word-count":"118","resourceName":"b04df404433e0a277c66074b508f034ab75c3949.rtf"}