{"Application-Name":"Microsoft Office Word","Author":"previd31","Character Count":"915","Company":"Microsoft","Content-Length":"26112","Content-Type":"application/msword","Creation-Date":"2020-06-09T20:31:00Z","Edit-Time":"4200000000","Keywords":"","Last-Author":"40050","Last-Modified":"2020-06-25T21:56:00Z","Last-Printed":"2020-06-09T18:17:00Z","Last-Save-Date":"2020-06-25T21:56:00Z","Page-Count":"1","Revision-Number":"8","Template":"Normal","Word-Count":"169","X-Parsed-By":["org.apache.tika.parser.DefaultParser","org.apache.tika.parser.microsoft.OfficeParser"],"cp:revision":"8","cp:subject":"","creator":"previd31","date":"2020-06-25T21:56:00Z","dc:creator":"previd31","dc:subject":"","dc:title":"","dcterms:created":"2020-06-09T20:31:00Z","dcterms:modified":"2020-06-25T21:56:00Z","extended-properties:Application":"Microsoft Office Word","extended-properties:Company":"Microsoft","extended-properties:Template":"Normal","meta:author":"previd31","meta:character-count":"915","meta:creation-date":"2020-06-09T20:31:00Z","meta:keyword":"","meta:last-author":"40050","meta:page-count":"1","meta:print-date":"2020-06-09T18:17:00Z","meta:save-date":"2020-06-25T21:56:00Z","meta:word-count":"169","modified":"2020-06-25T21:56:00Z","resourceName":"325e69078c842aabaf2621d37222aa4523c3774a.doc","subject":"","title":"","xmpTPg:NPages":"1"}