{"Application-Name":"Microsoft Office Word","Author":"Gabinete2","Character Count":"989","Company":"","Content-Length":"82432","Content-Type":"application/msword","Creation-Date":"2020-02-17T20:39:00Z","Edit-Time":"3000000000","Last-Author":"Usuario","Last-Modified":"2020-02-17T20:39:00Z","Last-Printed":"2020-02-17T20:39:00Z","Last-Save-Date":"2020-02-17T20:39:00Z","Page-Count":"1","Revision-Number":"2","Template":"Normal","Word-Count":"182","X-Parsed-By":["org.apache.tika.parser.DefaultParser","org.apache.tika.parser.microsoft.OfficeParser"],"cp:revision":"2","creator":"Gabinete2","date":"2020-02-17T20:39:00Z","dc:creator":"Gabinete2","dc:title":"DECRETO Nº","dcterms:created":"2020-02-17T20:39:00Z","dcterms:modified":"2020-02-17T20:39:00Z","extended-properties:Application":"Microsoft Office Word","extended-properties:Company":"","extended-properties:Template":"Normal","meta:author":"Gabinete2","meta:character-count":"989","meta:creation-date":"2020-02-17T20:39:00Z","meta:last-author":"Usuario","meta:page-count":"1","meta:print-date":"2020-02-17T20:39:00Z","meta:save-date":"2020-02-17T20:39:00Z","meta:word-count":"182","modified":"2020-02-17T20:39:00Z","resourceName":"31c4040f7174686d4be6c131de1545b18b9e2dcb.doc","title":"DECRETO Nº","xmpTPg:NPages":"1"}