{"Author":"edimar.benetti","Content-Length":"50607","Content-Type":"application/pdf","Creation-Date":"2020-10-28T18:12:25Z","Keywords":"","Last-Modified":"2020-10-28T18:12:25Z","Last-Save-Date":"2020-10-28T18:12:25Z","X-Parsed-By":["org.apache.tika.parser.DefaultParser","org.apache.tika.parser.pdf.PDFParser"],"access_permission:assemble_document":"true","access_permission:can_modify":"true","access_permission:can_print":"true","access_permission:can_print_degraded":"true","access_permission:extract_content":"true","access_permission:extract_for_accessibility":"true","access_permission:fill_in_form":"true","access_permission:modify_annotations":"true","cp:subject":"","created":"2020-10-28T18:12:25Z","creator":"edimar.benetti","date":"2020-10-28T18:12:25Z","dc:creator":"edimar.benetti","dc:format":"application/pdf; version\u003d1.4","dc:subject":"","dc:title":"Decreto_6.844_Diário","dcterms:created":"2020-10-28T18:12:25Z","dcterms:modified":"2020-10-28T18:12:25Z","meta:author":"edimar.benetti","meta:creation-date":"2020-10-28T18:12:25Z","meta:keyword":"","meta:save-date":"2020-10-28T18:12:25Z","modified":"2020-10-28T18:12:25Z","pdf:PDFVersion":"1.4","pdf:charsPerPage":"1555","pdf:docinfo:created":"2020-10-28T18:12:25Z","pdf:docinfo:creator":"edimar.benetti","pdf:docinfo:creator_tool":"PDFCreator 3.3.0.2468","pdf:docinfo:keywords":"","pdf:docinfo:modified":"2020-10-28T18:12:25Z","pdf:docinfo:producer":"PDFCreator 3.3.0.2468","pdf:docinfo:subject":"","pdf:docinfo:title":"Decreto_6.844_Diário","pdf:encrypted":"false","pdf:hasMarkedContent":"false","pdf:hasXFA":"false","pdf:hasXMP":"true","pdf:unmappedUnicodeCharsPerPage":"0","producer":"PDFCreator 3.3.0.2468","resourceName":"8d5ba41c9e9dffc077c85eb9d23ee6f9c456393b.pdf","subject":"","title":"Decreto_6.844_Diário","xmp:CreatorTool":"PDFCreator 3.3.0.2468","xmpMM:DocumentID":"uuid:a17da1af-1ba4-11eb-0000-4194bff8ae3f","xmpTPg:NPages":"1"}