{"Application-Name":"Microsoft Office Word","Author":"P.M.S.J","Character Count":"2353","Company":"Microsoft","Content-Length":"125952","Content-Type":"application/msword","Creation-Date":"2019-12-30T17:53:00Z","Edit-Time":"600000000","Last-Author":"humberto.silva","Last-Modified":"2019-12-30T17:53:00Z","Last-Printed":"2019-12-30T17:46:00Z","Last-Save-Date":"2019-12-30T17:53:00Z","Page-Count":"2","Revision-Number":"2","Template":"Normal.dotm","Word-Count":"435","X-Parsed-By":["org.apache.tika.parser.DefaultParser","org.apache.tika.parser.microsoft.OfficeParser"],"cp:revision":"2","creator":"P.M.S.J","date":"2019-12-30T17:53:00Z","dc:creator":"P.M.S.J","dc:title":"SECRETARIA MUNICIPALDAADMINISTRAÇÃO","dcterms:created":"2019-12-30T17:53:00Z","dcterms:modified":"2019-12-30T17:53:00Z","extended-properties:Application":"Microsoft Office Word","extended-properties:Company":"Microsoft","extended-properties:Template":"Normal.dotm","meta:author":"P.M.S.J","meta:character-count":"2353","meta:creation-date":"2019-12-30T17:53:00Z","meta:last-author":"humberto.silva","meta:page-count":"2","meta:print-date":"2019-12-30T17:46:00Z","meta:save-date":"2019-12-30T17:53:00Z","meta:word-count":"435","modified":"2019-12-30T17:53:00Z","resourceName":"ee4707a61f6c1c884e72764f8f68025c397f88eb.doc","title":"SECRETARIA MUNICIPALDAADMINISTRAÇÃO","xmpTPg:NPages":"2"}