{"Application-Name":"Microsoft Office Word","Author":"usuario","Character Count":"1037","Company":"Microsoft","Content-Length":"40448","Content-Type":"application/msword","Creation-Date":"2020-08-27T17:02:00Z","Edit-Time":"1200000000","Last-Author":"Usuário","Last-Modified":"2020-08-27T17:14:00Z","Last-Printed":"2020-08-27T17:14:00Z","Last-Save-Date":"2020-08-27T17:14:00Z","Page-Count":"1","Revision-Number":"4","Template":"Edital Concurso nº 03 2001.dot","Word-Count":"191","X-Parsed-By":["org.apache.tika.parser.DefaultParser","org.apache.tika.parser.microsoft.OfficeParser"],"cp:revision":"4","creator":"usuario","custom:KSOProductBuildVer":"1046-11.2.0.8641","date":"2020-08-27T17:14:00Z","dc:creator":"usuario","dcterms:created":"2020-08-27T17:02:00Z","dcterms:modified":"2020-08-27T17:14:00Z","extended-properties:Application":"Microsoft Office Word","extended-properties:Company":"Microsoft","extended-properties:Template":"Edital Concurso nº 03 2001.dot","meta:author":"usuario","meta:character-count":"1037","meta:creation-date":"2020-08-27T17:02:00Z","meta:last-author":"Usuário","meta:page-count":"1","meta:print-date":"2020-08-27T17:14:00Z","meta:save-date":"2020-08-27T17:14:00Z","meta:word-count":"191","modified":"2020-08-27T17:14:00Z","resourceName":"a245cbb19558ba5886781e1b52a024bf0f18f5cc.doc","xmpTPg:NPages":"1"}