{"Application-Name":"LibreOffice/5.1.0.3$Windows_X86_64 LibreOffice_project/5e3e00a007d9b3b6efb6797a8b8e57b51ab1f737","Author":"07","Character Count":"1370","Character-Count-With-Spaces":"1604","Content-Length":"32992","Content-Type":"application/vnd.openxmlformats-officedocument.wordprocessingml.document","Creation-Date":"2014-07-03T13:24:00Z","Last-Modified":"2020-02-27T17:47:20Z","Last-Printed":"2019-07-01T19:37:09Z","Last-Save-Date":"2020-02-27T17:47:20Z","Page-Count":"1","Paragraph-Count":"12","Revision-Number":"5","Template":"Normal","Total-Time":"9","Word-Count":"240","X-Parsed-By":["org.apache.tika.parser.DefaultParser","org.apache.tika.parser.microsoft.ooxml.OOXMLParser"],"cp:revision":"5","creator":"07","custom:DocSecurity":"0","custom:KSOProductBuildVer":"1046-11.2.0.8641","custom:LinksUpToDate":"false","custom:ScaleCrop":"false","date":"2020-02-27T17:47:20Z","dc:creator":"07","dc:language":"pt-BR","dcterms:created":"2014-07-03T13:24:00Z","dcterms:modified":"2020-02-27T17:47:20Z","extended-properties:Application":"LibreOffice/5.1.0.3$Windows_X86_64 LibreOffice_project/5e3e00a007d9b3b6efb6797a8b8e57b51ab1f737","extended-properties:DocSecurityString":"None","extended-properties:Template":"Normal","extended-properties:TotalTime":"9","language":"pt-BR","meta:author":"07","meta:character-count":"1370","meta:character-count-with-spaces":"1604","meta:creation-date":"2014-07-03T13:24:00Z","meta:page-count":"1","meta:paragraph-count":"12","meta:print-date":"2019-07-01T19:37:09Z","meta:save-date":"2020-02-27T17:47:20Z","meta:word-count":"240","modified":"2020-02-27T17:47:20Z","resourceName":"960d0cb7966d2c473922b65b7cfc77ad902f3c8f.docx","xmpTPg:NPages":"1"}