{"Application-Name":"Microsoft Office Word","Author":"Prefeitura de Blumenau","Character Count":"759","Company":"Prefeitura de Blumenau","Content-Length":"28160","Content-Type":"application/msword","Creation-Date":"2020-11-17T13:27:00Z","Edit-Time":"107400000000","Last-Author":"40001","Last-Modified":"2020-11-17T17:02:00Z","Last-Printed":"2020-11-17T16:10:00Z","Last-Save-Date":"2020-11-17T17:02:00Z","Page-Count":"1","Revision-Number":"9","Template":"Normal","Word-Count":"140","X-Parsed-By":["org.apache.tika.parser.DefaultParser","org.apache.tika.parser.microsoft.OfficeParser"],"cp:revision":"9","creator":"Prefeitura de Blumenau","date":"2020-11-17T17:02:00Z","dc:creator":"Prefeitura de Blumenau","dc:title":"PORTARIA N","dcterms:created":"2020-11-17T13:27:00Z","dcterms:modified":"2020-11-17T17:02:00Z","extended-properties:Application":"Microsoft Office Word","extended-properties:Company":"Prefeitura de Blumenau","extended-properties:Template":"Normal","meta:author":"Prefeitura de Blumenau","meta:character-count":"759","meta:creation-date":"2020-11-17T13:27:00Z","meta:last-author":"40001","meta:page-count":"1","meta:print-date":"2020-11-17T16:10:00Z","meta:save-date":"2020-11-17T17:02:00Z","meta:word-count":"140","modified":"2020-11-17T17:02:00Z","resourceName":"b8500f369f871d176b4dc509f6134ed907ef1149.doc","title":"PORTARIA N","xmpTPg:NPages":"1"}