{"Application-Name":"Microsoft Office Word","Application-Version":"16.0000","Author":"Casa","Character Count":"3800","Character-Count-With-Spaces":"4495","Content-Length":"17276","Content-Type":"application/vnd.openxmlformats-officedocument.wordprocessingml.document","Creation-Date":"2020-10-23T17:17:00Z","Last-Author":"Aldinar Kirmse Pereira","Last-Modified":"2020-10-23T18:06:00Z","Last-Save-Date":"2020-10-23T18:06:00Z","Line-Count":"31","Page-Count":"3","Paragraph-Count":"8","Revision-Number":"11","Template":"Normal","Total-Time":"44","Word-Count":"703","X-Parsed-By":["org.apache.tika.parser.DefaultParser","org.apache.tika.parser.microsoft.ooxml.OOXMLParser"],"cp:revision":"11","creator":"Casa","date":"2020-10-23T18:06:00Z","dc:creator":"Casa","dc:publisher":"","dcterms:created":"2020-10-23T17:17:00Z","dcterms:modified":"2020-10-23T18:06:00Z","extended-properties:AppVersion":"16.0000","extended-properties:Application":"Microsoft Office Word","extended-properties:Company":"","extended-properties:DocSecurityString":"None","extended-properties:Template":"Normal","extended-properties:TotalTime":"44","meta:author":"Casa","meta:character-count":"3800","meta:character-count-with-spaces":"4495","meta:creation-date":"2020-10-23T17:17:00Z","meta:last-author":"Aldinar Kirmse Pereira","meta:line-count":"31","meta:page-count":"3","meta:paragraph-count":"8","meta:save-date":"2020-10-23T18:06:00Z","meta:word-count":"703","modified":"2020-10-23T18:06:00Z","publisher":"","resourceName":"65d4d8c91815c42407828c62f5d4e0858b12cc41.docx","xmpTPg:NPages":"3"}