{"Author":"Prefeitura Mun. de Serra.","Content-Length":"282412","Content-Type":"application/pdf","Creation-Date":"2020-08-28T19:35:17Z","Last-Modified":"2020-08-28T19:35:17Z","Last-Save-Date":"2020-08-28T19:35:17Z","X-Parsed-By":["org.apache.tika.parser.DefaultParser","org.apache.tika.parser.pdf.PDFParser"],"access_permission:assemble_document":"true","access_permission:can_modify":"true","access_permission:can_print":"true","access_permission:can_print_degraded":"true","access_permission:extract_content":"true","access_permission:extract_for_accessibility":"true","access_permission:fill_in_form":"true","access_permission:modify_annotations":"true","created":"2020-08-28T19:35:17Z","creator":"Prefeitura Mun. de Serra.","date":"2020-08-28T19:35:17Z","dc:creator":"Prefeitura Mun. de Serra.","dc:format":"application/pdf; version\u003d1.5","dc:language":"pt-BR","dc:title":" ","dcterms:created":"2020-08-28T19:35:17Z","dcterms:modified":"2020-08-28T19:35:17Z","language":"pt-BR","meta:author":"Prefeitura Mun. de Serra.","meta:creation-date":"2020-08-28T19:35:17Z","meta:save-date":"2020-08-28T19:35:17Z","modified":"2020-08-28T19:35:17Z","pdf:PDFVersion":"1.5","pdf:charsPerPage":["4041","3374","3243","3549","4428","646","1156","3353","2201","388","179","886"],"pdf:docinfo:created":"2020-08-28T19:35:17Z","pdf:docinfo:creator":"Prefeitura Mun. de Serra.","pdf:docinfo:creator_tool":"Microsoft速 Word 2016","pdf:docinfo:modified":"2020-08-28T19:35:17Z","pdf:docinfo:producer":"Microsoft速 Word 2016","pdf:docinfo:title":" ","pdf:encrypted":"false","pdf:hasMarkedContent":"true","pdf:hasXFA":"false","pdf:hasXMP":"false","pdf:unmappedUnicodeCharsPerPage":["0","0","0","0","0","0","0","0","0","0","0","0"],"producer":"Microsoft速 Word 2016","resourceName":"d77a8a00de27b14fa936b45292fee3f8ba1000f3.pdf","title":" ","xmp:CreatorTool":"Microsoft速 Word 2016","xmpTPg:NPages":"12"}