{"Application-Name":"Microsoft Office Word","Author":"PREFEITURA MUNICIPAL BLUMENAU","Character Count":"710","Company":"PREFEITURA MUNICIPAL BLUMENAU","Content-Length":"32768","Content-Type":"application/msword","Creation-Date":"2020-05-13T17:40:00Z","Last-Author":"Marcia da Silva","Last-Modified":"2020-05-13T17:40:00Z","Last-Printed":"2013-07-30T18:32:00Z","Last-Save-Date":"2020-05-13T17:40:00Z","Page-Count":"1","Revision-Number":"2","Template":"Normal","Word-Count":"131","X-Parsed-By":["org.apache.tika.parser.DefaultParser","org.apache.tika.parser.microsoft.OfficeParser"],"cp:revision":"2","creator":"PREFEITURA MUNICIPAL BLUMENAU","date":"2020-05-13T17:40:00Z","dc:creator":"PREFEITURA MUNICIPAL BLUMENAU","dc:title":"SECRETARIA DE ADMINISTRAÇÃO","dcterms:created":"2020-05-13T17:40:00Z","dcterms:modified":"2020-05-13T17:40:00Z","extended-properties:Application":"Microsoft Office Word","extended-properties:Company":"PREFEITURA MUNICIPAL BLUMENAU","extended-properties:Template":"Normal","meta:author":"PREFEITURA MUNICIPAL BLUMENAU","meta:character-count":"710","meta:creation-date":"2020-05-13T17:40:00Z","meta:last-author":"Marcia da Silva","meta:page-count":"1","meta:print-date":"2013-07-30T18:32:00Z","meta:save-date":"2020-05-13T17:40:00Z","meta:word-count":"131","modified":"2020-05-13T17:40:00Z","resourceName":"5fe0ec2b8b2be2c7dfe92585cf523a2da79d2fe6.doc","title":"SECRETARIA DE ADMINISTRAÇÃO","xmpTPg:NPages":"1"}