{"Author":"Victor Nascimento Esteves","Content-Length":"13312","Content-Type":"application/msword","Creation-Date":"2019-04-05T16:54:00Z","Edit-Time":"6850000000","Last-Modified":"2020-10-21T18:56:08Z","Last-Printed":"2019-05-02T18:39:00Z","Last-Save-Date":"2020-10-21T18:56:08Z","Revision-Number":"11","Template":"Normal","X-Parsed-By":["org.apache.tika.parser.DefaultParser","org.apache.tika.parser.microsoft.OfficeParser"],"cp:revision":"11","creator":"Victor Nascimento Esteves","custom:KSOProductBuildVer":"1046-10.2.0.7516","date":"2020-10-21T18:56:08Z","dc:creator":"Victor Nascimento Esteves","dcterms:created":"2019-04-05T16:54:00Z","dcterms:modified":"2020-10-21T18:56:08Z","extended-properties:Template":"Normal","meta:author":"Victor Nascimento Esteves","meta:creation-date":"2019-04-05T16:54:00Z","meta:print-date":"2019-05-02T18:39:00Z","meta:save-date":"2020-10-21T18:56:08Z","modified":"2020-10-21T18:56:08Z","resourceName":"bde6cdd0bfc1f8b3da18b25ca7b8b9ac8434df5a.doc"}