{"Author":"Ruth Alves Pereira","Content-Length":"80090","Content-Type":"application/rtf","Creation-Date":"2020-02-27T15:17:00Z","X-Parsed-By":["org.apache.tika.parser.DefaultParser","org.apache.tika.parser.rtf.RTFParser"],"creator":"Ruth Alves Pereira","dc:creator":"Ruth Alves Pereira","dcterms:created":"2020-02-27T15:17:00Z","meta:author":"Ruth Alves Pereira","meta:character-count":"734","meta:creation-date":"2020-02-27T15:17:00Z","meta:page-count":"1","meta:word-count":"135","resourceName":"22765dac972cb34b7c5832efd97a42691d10af88.rtf"}