{"Application-Name":"Microsoft Office Word","Application-Version":"16.0000","Author":"Darcy Lopes Costa","Character Count":"2062","Character-Count-With-Spaces":"2439","Content-Length":"23214","Content-Type":"application/vnd.openxmlformats-officedocument.wordprocessingml.document","Creation-Date":"2020-11-18T14:26:00Z","Last-Author":"Matheus de Almeida Tamandaré","Last-Modified":"2020-11-18T14:26:00Z","Last-Printed":"2020-11-13T17:12:00Z","Last-Save-Date":"2020-11-18T14:26:00Z","Line-Count":"17","Page-Count":"2","Paragraph-Count":"4","Revision-Number":"2","Template":"Normal","Total-Time":"1","Word-Count":"381","X-Parsed-By":["org.apache.tika.parser.DefaultParser","org.apache.tika.parser.microsoft.ooxml.OOXMLParser"],"cp:revision":"2","creator":"Darcy Lopes Costa","custom:KSOProductBuildVer":"1046-11.2.0.8888","date":"2020-11-18T14:26:00Z","dc:creator":"Darcy Lopes Costa","dc:publisher":"Hewlett-Packard Company","dcterms:created":"2020-11-18T14:26:00Z","dcterms:modified":"2020-11-18T14:26:00Z","extended-properties:AppVersion":"16.0000","extended-properties:Application":"Microsoft Office Word","extended-properties:Company":"Hewlett-Packard Company","extended-properties:DocSecurityString":"None","extended-properties:Template":"Normal","extended-properties:TotalTime":"1","meta:author":"Darcy Lopes Costa","meta:character-count":"2062","meta:character-count-with-spaces":"2439","meta:creation-date":"2020-11-18T14:26:00Z","meta:last-author":"Matheus de Almeida Tamandaré","meta:line-count":"17","meta:page-count":"2","meta:paragraph-count":"4","meta:print-date":"2020-11-13T17:12:00Z","meta:save-date":"2020-11-18T14:26:00Z","meta:word-count":"381","modified":"2020-11-18T14:26:00Z","publisher":"Hewlett-Packard Company","resourceName":"7cc020c5b09bbb4c17541d8b84ccc29ecddff642.docx","xmpTPg:NPages":"2"}