{"Author":"Priscila Baeta","Content-Length":"229789","Content-Type":"application/pdf","Creation-Date":"2020-12-02T10:52:12Z","X-Parsed-By":["org.apache.tika.parser.DefaultParser","org.apache.tika.parser.pdf.PDFParser"],"access_permission:assemble_document":"true","access_permission:can_modify":"true","access_permission:can_print":"true","access_permission:can_print_degraded":"true","access_permission:extract_content":"true","access_permission:extract_for_accessibility":"true","access_permission:fill_in_form":"true","access_permission:modify_annotations":"true","created":"2020-12-02T10:52:12Z","creator":"Priscila Baeta","dc:creator":"Priscila Baeta","dc:format":"application/pdf; version\u003d1.4","dc:language":"pt-BR","dcterms:created":"2020-12-02T10:52:12Z","language":"pt-BR","meta:author":"Priscila Baeta","meta:creation-date":"2020-12-02T10:52:12Z","pdf:PDFVersion":"1.4","pdf:charsPerPage":["1818","2069","2291","3089","2628","2680","2305","2739","2297","2453","2549","2018","1390","2297","2603"],"pdf:docinfo:created":"2020-12-02T10:52:12Z","pdf:docinfo:creator":"Priscila Baeta","pdf:docinfo:creator_tool":"Writer","pdf:docinfo:producer":"LibreOffice 5.1","pdf:encrypted":"false","pdf:hasMarkedContent":"false","pdf:hasXFA":"false","pdf:hasXMP":"false","pdf:unmappedUnicodeCharsPerPage":["0","0","0","0","0","0","0","0","0","0","0","0","0","0","0"],"producer":"LibreOffice 5.1","resourceName":"1236684dcdc960b57ac0b2d5851344dede2d379c.pdf","xmp:CreatorTool":"Writer","xmpTPg:NPages":"15"}