{"Application-Name":"Microsoft Office Word","Author":"32514","Character Count":"12042","Company":"Prefeitura Municipal de Blumenau","Content-Length":"295936","Content-Type":"application/msword","Creation-Date":"2020-06-10T16:58:00Z","Edit-Time":"25800000000","Last-Author":"228246","Last-Modified":"2020-06-10T17:49:00Z","Last-Save-Date":"2020-06-10T17:49:00Z","Page-Count":"4","Revision-Number":"4","Template":"Normal.dotm","Word-Count":"2230","X-Parsed-By":["org.apache.tika.parser.DefaultParser","org.apache.tika.parser.microsoft.OfficeParser"],"cp:revision":"4","creator":"32514","date":"2020-06-10T17:49:00Z","dc:creator":"32514","dc:title":"CONCEDER LICENÇA ESPECIAL À GESTANTE","dcterms:created":"2020-06-10T16:58:00Z","dcterms:modified":"2020-06-10T17:49:00Z","extended-properties:Application":"Microsoft Office Word","extended-properties:Company":"Prefeitura Municipal de Blumenau","extended-properties:Template":"Normal.dotm","meta:author":"32514","meta:character-count":"12042","meta:creation-date":"2020-06-10T16:58:00Z","meta:last-author":"228246","meta:page-count":"4","meta:save-date":"2020-06-10T17:49:00Z","meta:word-count":"2230","modified":"2020-06-10T17:49:00Z","resourceName":"563296ece070df5da8f0e81960834e6bc2fc645d.doc","title":"CONCEDER LICENÇA ESPECIAL À GESTANTE","xmpTPg:NPages":"4"}