{"Application-Name":"Microsoft Office Word","Application-Version":"16.0000","Author":"Secretaria de Assistencia Social","Character Count":"4078","Character-Count-With-Spaces":"4824","Content-Length":"178557","Content-Type":"application/vnd.openxmlformats-officedocument.wordprocessingml.document","Creation-Date":"2020-06-10T21:10:00Z","Last-Author":"Junior Spies","Last-Modified":"2020-06-10T21:19:00Z","Last-Printed":"2020-06-04T21:17:00Z","Last-Save-Date":"2020-06-10T21:19:00Z","Line-Count":"33","Page-Count":"3","Paragraph-Count":"9","Revision-Number":"6","Template":"Normal","Total-Time":"10","Word-Count":"755","X-Parsed-By":["org.apache.tika.parser.DefaultParser","org.apache.tika.parser.microsoft.ooxml.OOXMLParser"],"cp:revision":"6","creator":"Secretaria de Assistencia Social","date":"2020-06-10T21:19:00Z","dc:creator":"Secretaria de Assistencia Social","dc:publisher":"Prefeitura Municipal de São José","dcterms:created":"2020-06-10T21:10:00Z","dcterms:modified":"2020-06-10T21:19:00Z","extended-properties:AppVersion":"16.0000","extended-properties:Application":"Microsoft Office Word","extended-properties:Company":"Prefeitura Municipal de São José","extended-properties:DocSecurityString":"None","extended-properties:Template":"Normal","extended-properties:TotalTime":"10","meta:author":"Secretaria de Assistencia Social","meta:character-count":"4078","meta:character-count-with-spaces":"4824","meta:creation-date":"2020-06-10T21:10:00Z","meta:last-author":"Junior Spies","meta:line-count":"33","meta:page-count":"3","meta:paragraph-count":"9","meta:print-date":"2020-06-04T21:17:00Z","meta:save-date":"2020-06-10T21:19:00Z","meta:word-count":"755","modified":"2020-06-10T21:19:00Z","publisher":"Prefeitura Municipal de São José","resourceName":"67e9e34e92830738de37d4d1c1cd189fe5912553.docx","xmpTPg:NPages":"3"}