{"Application-Name":"Microsoft Office Word","Application-Version":"12.0000","Author":"marilia.formento","Character Count":"1057","Character-Count-With-Spaces":"1250","Content-Length":"93638","Content-Type":"application/vnd.openxmlformats-officedocument.wordprocessingml.document","Creation-Date":"2020-02-20T19:56:00Z","Last-Author":"Jr Coelho","Last-Modified":"2020-02-20T20:43:00Z","Last-Printed":"2018-11-30T19:17:00Z","Last-Save-Date":"2020-02-20T20:43:00Z","Line-Count":"8","Page-Count":"1","Paragraph-Count":"2","Revision-Number":"4","Template":"Normal.dotm","Total-Time":"16","Word-Count":"195","X-Parsed-By":["org.apache.tika.parser.DefaultParser","org.apache.tika.parser.microsoft.ooxml.OOXMLParser"],"cp:revision":"4","creator":"marilia.formento","custom:AppVersion":"12.0000","custom:Company":"Microsoft","custom:DocSecurity":"0","custom:HyperlinksChanged":"false","custom:LinksUpToDate":"false","custom:ScaleCrop":"false","custom:ShareDoc":"false","date":"2020-02-20T20:43:00Z","dc:creator":"marilia.formento","dc:language":"pt-BR","dc:publisher":"Microsoft","dcterms:created":"2020-02-20T19:56:00Z","dcterms:modified":"2020-02-20T20:43:00Z","extended-properties:AppVersion":"12.0000","extended-properties:Application":"Microsoft Office Word","extended-properties:Company":"Microsoft","extended-properties:DocSecurityString":"None","extended-properties:Template":"Normal.dotm","extended-properties:TotalTime":"16","language":"pt-BR","meta:author":"marilia.formento","meta:character-count":"1057","meta:character-count-with-spaces":"1250","meta:creation-date":"2020-02-20T19:56:00Z","meta:last-author":"Jr Coelho","meta:line-count":"8","meta:page-count":"1","meta:paragraph-count":"2","meta:print-date":"2018-11-30T19:17:00Z","meta:save-date":"2020-02-20T20:43:00Z","meta:word-count":"195","modified":"2020-02-20T20:43:00Z","publisher":"Microsoft","resourceName":"10f2cc3273667808c095e2c3bf01ddf682f26b33.docx","xmpTPg:NPages":"1"}