{"Application-Name":"Microsoft Office Word","Author":"186406","Character Count":"384","Company":"Prefeitura Municipal de Blumenau","Content-Length":"29184","Content-Type":"application/msword","Creation-Date":"2020-11-24T19:42:00Z","Edit-Time":"600000000","Keywords":"","Last-Author":"103381","Last-Modified":"2020-11-24T20:02:00Z","Last-Printed":"2014-05-09T18:29:00Z","Last-Save-Date":"2020-11-24T20:02:00Z","Page-Count":"1","Revision-Number":"4","Template":"Normal.dot","Word-Count":"70","X-Parsed-By":["org.apache.tika.parser.DefaultParser","org.apache.tika.parser.microsoft.OfficeParser"],"cp:revision":"4","cp:subject":"","creator":"186406","date":"2020-11-24T20:02:00Z","dc:creator":"186406","dc:subject":"","dc:title":" ","dcterms:created":"2020-11-24T19:42:00Z","dcterms:modified":"2020-11-24T20:02:00Z","extended-properties:Application":"Microsoft Office Word","extended-properties:Company":"Prefeitura Municipal de Blumenau","extended-properties:Template":"Normal.dot","meta:author":"186406","meta:character-count":"384","meta:creation-date":"2020-11-24T19:42:00Z","meta:keyword":"","meta:last-author":"103381","meta:page-count":"1","meta:print-date":"2014-05-09T18:29:00Z","meta:save-date":"2020-11-24T20:02:00Z","meta:word-count":"70","modified":"2020-11-24T20:02:00Z","resourceName":"a3ad2f2872f51b86d7efd7a8feb408f6bf7b673c.doc","subject":"","title":" ","xmpTPg:NPages":"1"}