{"Application-Name":"Microsoft Office Word","Application-Version":"14.0000","Author":"PREFEITURA MUNICIPAL BLUMENAU","Character Count":"858","Character-Count-With-Spaces":"954","Content-Length":"23555","Content-Type":"application/vnd.openxmlformats-officedocument.wordprocessingml.document","Creation-Date":"2020-08-28T14:24:00Z","Last-Author":"218588","Last-Modified":"2020-08-28T14:26:00Z","Last-Printed":"2020-08-28T14:25:00Z","Last-Save-Date":"2020-08-28T14:26:00Z","Line-Count":"7","Page-Count":"1","Paragraph-Count":"1","Revision-Number":"3","Template":"Normal.dotm","Total-Time":"2","Word-Count":"97","X-Parsed-By":["org.apache.tika.parser.DefaultParser","org.apache.tika.parser.microsoft.ooxml.OOXMLParser"],"cp:revision":"3","creator":"PREFEITURA MUNICIPAL BLUMENAU","date":"2020-08-28T14:26:00Z","dc:creator":"PREFEITURA MUNICIPAL BLUMENAU","dc:publisher":"PREFEITURA MUNICIPAL BLUMENAU","dc:title":"SECRETARIA DE ADMINISTRAÇÃO","dcterms:created":"2020-08-28T14:24:00Z","dcterms:modified":"2020-08-28T14:26:00Z","extended-properties:AppVersion":"14.0000","extended-properties:Application":"Microsoft Office Word","extended-properties:Company":"PREFEITURA MUNICIPAL BLUMENAU","extended-properties:DocSecurityString":"None","extended-properties:Template":"Normal.dotm","extended-properties:TotalTime":"2","meta:author":"PREFEITURA MUNICIPAL BLUMENAU","meta:character-count":"858","meta:character-count-with-spaces":"954","meta:creation-date":"2020-08-28T14:24:00Z","meta:last-author":"218588","meta:line-count":"7","meta:page-count":"1","meta:paragraph-count":"1","meta:print-date":"2020-08-28T14:25:00Z","meta:save-date":"2020-08-28T14:26:00Z","meta:word-count":"97","modified":"2020-08-28T14:26:00Z","publisher":"PREFEITURA MUNICIPAL BLUMENAU","resourceName":"b4fbcc15af7b726eb1be034f280523a2e29448f6.docx","title":"SECRETARIA DE ADMINISTRAÇÃO","xmpTPg:NPages":"1"}