{"Application-Name":"Microsoft Office Word","Author":"usuario","Character Count":"2502","Company":"","Content-Length":"42496","Content-Type":"application/msword","Creation-Date":"2020-10-08T19:37:00Z","Keywords":"","Last-Author":"Matheus de Almeida Tamandaré","Last-Modified":"2020-10-08T19:37:00Z","Last-Printed":"2020-10-05T18:43:00Z","Last-Save-Date":"2020-10-08T19:37:00Z","Page-Count":"2","Revision-Number":"2","Template":"Normal","Word-Count":"463","X-Parsed-By":["org.apache.tika.parser.DefaultParser","org.apache.tika.parser.microsoft.OfficeParser"],"cp:revision":"2","cp:subject":"","creator":"usuario","date":"2020-10-08T19:37:00Z","dc:creator":"usuario","dc:subject":"","dc:title":" ","dcterms:created":"2020-10-08T19:37:00Z","dcterms:modified":"2020-10-08T19:37:00Z","extended-properties:Application":"Microsoft Office Word","extended-properties:Company":"","extended-properties:Template":"Normal","meta:author":"usuario","meta:character-count":"2502","meta:creation-date":"2020-10-08T19:37:00Z","meta:keyword":"","meta:last-author":"Matheus de Almeida Tamandaré","meta:page-count":"2","meta:print-date":"2020-10-05T18:43:00Z","meta:save-date":"2020-10-08T19:37:00Z","meta:word-count":"463","modified":"2020-10-08T19:37:00Z","resourceName":"c1b714fe352cfc4a3b1b4c30f4904f25de594be4.doc","subject":"","title":" ","xmpTPg:NPages":"2"}