{"Application-Name":"Microsoft Office Word","Author":"Prefeitura M Alto Bela Vista","Character Count":"1058","Company":"","Content-Length":"46592","Content-Type":"application/msword","Creation-Date":"2020-06-22T16:26:00Z","Edit-Time":"111600000000","Last-Author":"Usuário","Last-Modified":"2020-06-22T19:43:00Z","Last-Printed":"2020-06-22T19:43:00Z","Last-Save-Date":"2020-06-22T19:43:00Z","Page-Count":"1","Revision-Number":"7","Template":"Edital Concurso nº 03 2001.dot","Word-Count":"195","X-Parsed-By":["org.apache.tika.parser.DefaultParser","org.apache.tika.parser.microsoft.OfficeParser"],"cp:revision":"7","creator":"Prefeitura M Alto Bela Vista","date":"2020-06-22T19:43:00Z","dc:creator":"Prefeitura M Alto Bela Vista","dc:title":"CONCURSO PÚBLICO PARA PREENCHIMENTO DE VAGAS NO QUADRO DE PESSOAL DO PODER EXECUTIVO MUNIPAL","dcterms:created":"2020-06-22T16:26:00Z","dcterms:modified":"2020-06-22T19:43:00Z","extended-properties:Application":"Microsoft Office Word","extended-properties:Company":"","extended-properties:Template":"Edital Concurso nº 03 2001.dot","meta:author":"Prefeitura M Alto Bela Vista","meta:character-count":"1058","meta:creation-date":"2020-06-22T16:26:00Z","meta:last-author":"Usuário","meta:page-count":"1","meta:print-date":"2020-06-22T19:43:00Z","meta:save-date":"2020-06-22T19:43:00Z","meta:word-count":"195","modified":"2020-06-22T19:43:00Z","resourceName":"45168d3aee7393d22238cd5570b5e1a87886c066.doc","title":"CONCURSO PÚBLICO PARA PREENCHIMENTO DE VAGAS NO QUADRO DE PESSOAL DO PODER EXECUTIVO MUNIPAL","xmpTPg:NPages":"1"}