{"Application-Name":"Microsoft Office Word","Author":"Samae","Character Count":"1024","Company":"Hewlett-Packard Company","Content-Length":"27648","Content-Type":"application/msword","Creation-Date":"2020-01-20T15:34:00Z","Edit-Time":"4200000000","Keywords":"","Last-Author":"103381","Last-Modified":"2020-01-22T20:55:00Z","Last-Printed":"2016-04-25T10:35:00Z","Last-Save-Date":"2020-01-22T20:55:00Z","Page-Count":"1","Revision-Number":"4","Template":"Normal.dot","Word-Count":"189","X-Parsed-By":["org.apache.tika.parser.DefaultParser","org.apache.tika.parser.microsoft.OfficeParser"],"cp:revision":"4","cp:subject":"","creator":"Samae","date":"2020-01-22T20:55:00Z","dc:creator":"Samae","dc:subject":"","dc:title":"Blumenau, 10/09/2014","dcterms:created":"2020-01-20T15:34:00Z","dcterms:modified":"2020-01-22T20:55:00Z","extended-properties:Application":"Microsoft Office Word","extended-properties:Company":"Hewlett-Packard Company","extended-properties:Template":"Normal.dot","meta:author":"Samae","meta:character-count":"1024","meta:creation-date":"2020-01-20T15:34:00Z","meta:keyword":"","meta:last-author":"103381","meta:page-count":"1","meta:print-date":"2016-04-25T10:35:00Z","meta:save-date":"2020-01-22T20:55:00Z","meta:word-count":"189","modified":"2020-01-22T20:55:00Z","resourceName":"e01f3fc1dd49dcca562f2a06f6bc4a8e8e52ce40.doc","subject":"","title":"Blumenau, 10/09/2014","xmpTPg:NPages":"1"}