{"Application-Name":"Microsoft Office Word","Author":"Julio Augusto Souza Filho","Character Count":"843","Company":"Prefeitura de Blumenau","Content-Length":"1110016","Content-Type":"application/msword","Creation-Date":"2020-12-11T17:29:00Z","Edit-Time":"1800000000","Last-Author":"183350","Last-Modified":"2020-12-11T17:31:00Z","Last-Printed":"2018-07-26T18:48:00Z","Last-Save-Date":"2020-12-11T17:31:00Z","Page-Count":"1","Revision-Number":"3","Template":"Normal.dotm","Word-Count":"155","X-Parsed-By":["org.apache.tika.parser.DefaultParser","org.apache.tika.parser.microsoft.OfficeParser"],"cp:revision":"3","creator":"Julio Augusto Souza Filho","date":"2020-12-11T17:31:00Z","dc:creator":"Julio Augusto Souza Filho","dc:title":"DECRETO N","dcterms:created":"2020-12-11T17:29:00Z","dcterms:modified":"2020-12-11T17:31:00Z","extended-properties:Application":"Microsoft Office Word","extended-properties:Company":"Prefeitura de Blumenau","extended-properties:Template":"Normal.dotm","meta:author":"Julio Augusto Souza Filho","meta:character-count":"843","meta:creation-date":"2020-12-11T17:29:00Z","meta:last-author":"183350","meta:page-count":"1","meta:print-date":"2018-07-26T18:48:00Z","meta:save-date":"2020-12-11T17:31:00Z","meta:word-count":"155","modified":"2020-12-11T17:31:00Z","resourceName":"2c6278bcc514a95685e3b2cf2cbd4366639acd2f.doc","title":"DECRETO N","xmpTPg:NPages":"1"}