{"Application-Name":"Microsoft Office Word","Author":"Prefeitura M Alto Bela Vista","Character Count":"1727","Company":"","Content-Length":"62976","Content-Type":"application/msword","Creation-Date":"2020-01-29T17:46:00Z","Edit-Time":"19800000000","Last-Author":"Usuário","Last-Modified":"2020-01-30T17:34:00Z","Last-Printed":"2020-01-30T17:34:00Z","Last-Save-Date":"2020-01-30T17:34:00Z","Page-Count":"1","Revision-Number":"18","Template":"Edital Concurso nº 03 2001.dot","Word-Count":"319","X-Parsed-By":["org.apache.tika.parser.DefaultParser","org.apache.tika.parser.microsoft.OfficeParser"],"cp:revision":"18","creator":"Prefeitura M Alto Bela Vista","date":"2020-01-30T17:34:00Z","dc:creator":"Prefeitura M Alto Bela Vista","dc:title":"CONCURSO PÚBLICO PARA PREENCHIMENTO DE VAGAS NO QUADRO DE PESSOAL DO PODER EXECUTIVO MUNIPAL","dcterms:created":"2020-01-29T17:46:00Z","dcterms:modified":"2020-01-30T17:34:00Z","extended-properties:Application":"Microsoft Office Word","extended-properties:Company":"","extended-properties:Template":"Edital Concurso nº 03 2001.dot","meta:author":"Prefeitura M Alto Bela Vista","meta:character-count":"1727","meta:creation-date":"2020-01-29T17:46:00Z","meta:last-author":"Usuário","meta:page-count":"1","meta:print-date":"2020-01-30T17:34:00Z","meta:save-date":"2020-01-30T17:34:00Z","meta:word-count":"319","modified":"2020-01-30T17:34:00Z","resourceName":"55c9be7b386c6b64e2cf222d011911683414e7a9.doc","title":"CONCURSO PÚBLICO PARA PREENCHIMENTO DE VAGAS NO QUADRO DE PESSOAL DO PODER EXECUTIVO MUNIPAL","xmpTPg:NPages":"1"}